tqdm_pathos/__init__.py
tqdm_pathos/tqdm_pathos.py
tqdm_pathos-0.4.dist-info/LICENSE
tqdm_pathos-0.4.dist-info/METADATA
tqdm_pathos-0.4.dist-info/WHEEL
tqdm_pathos-0.4.dist-info/top_level.txt
tqdm_pathos-0.4.dist-info/RECORD
