Metadata-Version: 2.1
Name: tqdm_pathos
Version: 0.4
Summary: tqdm_pathos
Home-page: https://github.com/mdmould/tqdm_pathos
Author: Matthew Mould
Author-email: mattdmould@gmail.com
License: MIT
Requires-Python: >=3.7
License-File: LICENSE
Requires-Dist: pathos
Requires-Dist: tqdm
